{
  "books": [
    {
      "title": "clean code",
      "description": "about code",
      "id": "iTtJnGCpE"
    },
    {
      "title": "1 van cau hoi vi sao?",
      "description": "Why",
      "id": "uSsSK2ap-"
    },
    {
      "title": "code",
      "description": "kien",
      "id": "JO1Pxd7-M"
    },
    {
      "title": "toi thay hoa vang tren co xanh",
      "description": "Nguyen Nhat Anh",
      "id": "SMrywniV4"
    }
  ],
  "users": [
    {
      "name": "admin",
      "id": "vYPpSwUvl",
      "email": "admin@gmail.com",
      "password": "e10adc3949ba59abbe56e057f20f883e",
      "isAdmin": true
    },
    {
      "name": "hoa",
      "id": "ZlG0ScX7E",
      "email": "hoa@gmail.com",
      "password": "4297f44b13955235245b2497399d7a93",
      "isAdmin": false
    },
    {
      "name": "thang",
      "id": "54DFW02Gk",
      "email": "thang@gmail.com",
      "password": "4297f44b13955235245b2497399d7a93",
      "isAdmin": false
    },
    {
      "name": "hoang",
      "id": "DnuWXUmDR",
      "email": "hoang@gmail.com",
      "password": "4297f44b13955235245b2497399d7a93",
      "isAdmin": false
    },
    {
      "name": "khuong",
      "id": "8kM4qVVul",
      "email": "khuong@gmail.com",
      "password": "4297f44b13955235245b2497399d7a93",
      "isAdmin": false
    },
    {
      "name": "nam",
      "id": "JXsXBeoHv",
      "email": "nam@gmail.com",
      "password": "4297f44b13955235245b2497399d7a93",
      "isAdmin": false
    }
  ],
  "transactions": [
    {
      "id": "BctzQlOOs",
      "isComplete": false,
      "bookId": "iTtJnGCpE",
      "userId": "w_ruLjOsh",
      "content": "Kien got clean code."
    },
    {
      "id": "3gpSf0RH6",
      "isComplete": false,
      "bookId": "iTtJnGCpE",
      "userId": "BDMAhI9XP",
      "content": "hoa got clean code."
    },
    {
      "id": "lSsuo4fFq",
      "isComplete": false,
      "bookId": "JO1Pxd7-M",
      "userId": "BDMAhI9XP",
      "content": "hoa got code."
    },
    {
      "id": "KkJXP4MJ8",
      "isComplete": false,
      "bookId": "SMrywniV4",
      "userId": "SvwrCmgUC",
      "content": "thang got toi thay hoa vang tren co xanh."
    },
    {
      "id": "8k772O5Ce",
      "isComplete": true,
      "bookId": "SMrywniV4",
      "userId": "BDMAhI9XP",
      "content": "hoa got toi thay hoa vang tren co xanh."
    },
    {
      "id": "j2sEdw5aL",
      "isComplete": false,
      "bookId": "iTtJnGCpE",
      "userId": "5NvPQXIZW",
      "content": "thu got clean code."
    }
  ]
}