{
  "books": [
    {
      "title": "clean code",
      "description": "about code",
      "id": "iTtJnGCpE"
    },
    {
      "title": "1 van cau hoi vi sao?",
      "description": "Why",
      "id": "uSsSK2ap-"
    },
    {
      "title": "code",
      "description": "kien",
      "id": "JO1Pxd7-M"
    },
    {
      "title": "toi thay hoa vang tren co xanh",
      "description": "Nguyen Nhat Anh",
      "id": "SMrywniV4"
    }
  ],
  "users": [
    {
      "name": "Kien",
      "id": "w_ruLjOsh",
      "email": "kien@gmail.com",
      "password": "123456",
      "isAdmin": true
    },
    {
      "name": "hoa",
      "id": "BDMAhI9XP",
      "email": "hoa@gmail.com",
      "password": "123123",
      "isAdmin": false
    },
    {
      "name": "thang",
      "id": "SvwrCmgUC",
      "email": "thang@gmail.com",
      "password": "123123",
      "isAdmin": false
    },
    {
      "name": "thu",
      "id": "5NvPQXIZW",
      "email": "thu@gmail.com",
      "password": "123123",
      "isAdmin": false
    }
  ],
  "transactions": [
    {
      "id": "BctzQlOOs",
      "isComplete": false,
      "bookId": "iTtJnGCpE",
      "userId": "w_ruLjOsh",
      "content": "Kien got clean code."
    },
    {
      "id": "3gpSf0RH6",
      "isComplete": false,
      "bookId": "iTtJnGCpE",
      "userId": "BDMAhI9XP",
      "content": "hoa got clean code."
    },
    {
      "id": "lSsuo4fFq",
      "isComplete": false,
      "bookId": "JO1Pxd7-M",
      "userId": "BDMAhI9XP",
      "content": "hoa got code."
    },
    {
      "id": "KkJXP4MJ8",
      "isComplete": false,
      "bookId": "SMrywniV4",
      "userId": "SvwrCmgUC",
      "content": "thang got toi thay hoa vang tren co xanh."
    },
    {
      "id": "8k772O5Ce",
      "isComplete": true,
      "bookId": "SMrywniV4",
      "userId": "BDMAhI9XP",
      "content": "hoa got toi thay hoa vang tren co xanh."
    },
    {
      "id": "j2sEdw5aL",
      "isComplete": false,
      "bookId": "iTtJnGCpE",
      "userId": "5NvPQXIZW",
      "content": "thu got clean code."
    }
  ]
}